hypernode_api_python/__init__.py
hypernode_api_python/client.py
hypernode_api_python-0.0.6.dist-info/LICENSE
hypernode_api_python-0.0.6.dist-info/METADATA
hypernode_api_python-0.0.6.dist-info/WHEEL
hypernode_api_python-0.0.6.dist-info/top_level.txt
hypernode_api_python-0.0.6.dist-info/RECORD
