Metadata-Version: 2.1
Name: hypernode-api-python
Version: 0.0.6
Summary: "Hypernode API Client for Python"
Home-page: https://github.com/ByteInternet/hypernode_api_python
Author: Hypernode Team
Author-email: support@hypernode.com
License: MIT
Requires-Python: >=3.7
License-File: LICENSE
Requires-Dist: pip
Requires-Dist: requests
